<rdf:RDF
    xmlns:rdf="http://www.w3.org/1999/02/22-rdf-syntax-ns#"
    xmlns:adlgaz="http://adl-gazetteer.geog.ucsb.edu/ONT/ADL#">
  <rdf:Description rdf:about="http://adl-gazetteer.geog.ucsb.edu/ADL/rockville_bench">
    <adlgaz:hasID>6006409</adlgaz:hasID>
    <adlgaz:hasModifiedDate rdf:datatype="http://www.w3.org/2001/XMLSchema#date"
    >2004-02-25</adlgaz:hasModifiedDate>
    <adlgaz:hasEntryDate rdf:datatype="http://www.w3.org/2001/XMLSchema#date"
    >1999-07-23</adlgaz:hasEntryDate>
    <adlgaz:hasExtent>POINT (-113.0416717529296900 37.1727790832519530)</adlgaz:hasExtent>
    <adlgaz:hasSchema>ADL Feature Type Thesaurus</adlgaz:hasSchema>
    <adlgaz:hasDescription></adlgaz:hasDescription>
    <adlgaz:onPlanet>Earth</adlgaz:onPlanet>
    <adlgaz:hasAlternateName xml:lang="NULL">Rockville Bench</adlgaz:hasAlternateName>
    <adlgaz:hasPrimaryName xml:lang="en">"Rockville Bench"</adlgaz:hasPrimaryName>
  </rdf:Description>
  <rdf:Description rdf:about="http://adl-gazetteer.geog.ucsb.edu/ADL/price_bench">
    <adlgaz:hasID>6006405</adlgaz:hasID>
    <adlgaz:hasModifiedDate rdf:datatype="http://www.w3.org/2001/XMLSchema#date"
    >2004-02-25</adlgaz:hasModifiedDate>
    <adlgaz:hasEntryDate rdf:datatype="http://www.w3.org/2001/XMLSchema#date"
    >1999-07-23</adlgaz:hasEntryDate>
    <adlgaz:hasExtent>POINT (-113.5930633544921900 37.0533294677734380)</adlgaz:hasExtent>
    <adlgaz:hasSchema>ADL Feature Type Thesaurus</adlgaz:hasSchema>
    <adlgaz:hasDescription></adlgaz:hasDescription>
    <adlgaz:onPlanet>Earth</adlgaz:onPlanet>
    <adlgaz:hasAlternateName xml:lang="NULL">Price Bench</adlgaz:hasAlternateName>
    <adlgaz:hasPrimaryName xml:lang="en">"Price Bench"</adlgaz:hasPrimaryName>
  </rdf:Description>
  <rdf:Description rdf:about="http://adl-gazetteer.geog.ucsb.edu/ADL/red_benches">
    <adlgaz:hasID>6006407</adlgaz:hasID>
    <adlgaz:hasModifiedDate rdf:datatype="http://www.w3.org/2001/XMLSchema#date"
    >2004-02-25</adlgaz:hasModifiedDate>
    <adlgaz:hasEntryDate rdf:datatype="http://www.w3.org/2001/XMLSchema#date"
    >1999-07-23</adlgaz:hasEntryDate>
    <adlgaz:hasExtent>MULTIPOINT(-110.34361267089844 37.982498168945312, -110.3477783203125 38.016670227050781, -110.37638854980469 38.041671752929688)</adlgaz:hasExtent>
    <adlgaz:hasSchema>ADL Feature Type Thesaurus</adlgaz:hasSchema>
    <adlgaz:hasDescription></adlgaz:hasDescription>
    <adlgaz:onPlanet>Earth</adlgaz:onPlanet>
    <adlgaz:hasAlternateName xml:lang="NULL">Red Benches</adlgaz:hasAlternateName>
    <adlgaz:hasPrimaryName xml:lang="en">"Red Benches"</adlgaz:hasPrimaryName>
  </rdf:Description>
  <rdf:Description rdf:about="http://adl-gazetteer.geog.ucsb.edu/ADL/row_of_pines_bench">
    <adlgaz:hasID>6006411</adlgaz:hasID>
    <adlgaz:hasModifiedDate rdf:datatype="http://www.w3.org/2001/XMLSchema#date"
    >2004-02-25</adlgaz:hasModifiedDate>
    <adlgaz:hasEntryDate rdf:datatype="http://www.w3.org/2001/XMLSchema#date"
    >1999-07-23</adlgaz:hasEntryDate>
    <adlgaz:hasExtent>MULTIPOINT(-111.63944244384766 38.483329772949219, -111.64193725585938 38.501388549804688, -111.62444305419922 38.479171752929688, -111.62444305419922 38.504169464111328)</adlgaz:hasExtent>
    <adlgaz:hasSchema>ADL Feature Type Thesaurus</adlgaz:hasSchema>
    <adlgaz:hasDescription></adlgaz:hasDescription>
    <adlgaz:onPlanet>Earth</adlgaz:onPlanet>
    <adlgaz:hasAlternateName xml:lang="NULL">Row of Pines Bench</adlgaz:hasAlternateName>
    <adlgaz:hasPrimaryName xml:lang="en">"Row of Pines Bench"</adlgaz:hasPrimaryName>
  </rdf:Description>
  <rdf:Description rdf:about="http://adl-gazetteer.geog.ucsb.edu/ADL/porphyry_bench">
    <adlgaz:hasID>6006402</adlgaz:hasID>
    <adlgaz:hasModifiedDate rdf:datatype="http://www.w3.org/2001/XMLSchema#date"
    >2004-02-25</adlgaz:hasModifiedDate>
    <adlgaz:hasEntryDate rdf:datatype="http://www.w3.org/2001/XMLSchema#date"
    >1999-07-23</adlgaz:hasEntryDate>
    <adlgaz:hasExtent>POINT (-110.9338912963867200 39.5986099243164060)</adlgaz:hasExtent>
    <adlgaz:hasSchema>ADL Feature Type Thesaurus</adlgaz:hasSchema>
    <adlgaz:hasDescription></adlgaz:hasDescription>
    <adlgaz:onPlanet>Earth</adlgaz:onPlanet>
    <adlgaz:hasAlternateName xml:lang="NULL">Porphyry Bench</adlgaz:hasAlternateName>
    <adlgaz:hasPrimaryName xml:lang="en">"Porphyry Bench"</adlgaz:hasPrimaryName>
  </rdf:Description>
  <rdf:Description rdf:about="http://adl-gazetteer.geog.ucsb.edu/ADL/poverty_bench">
    <adlgaz:hasID>6006403</adlgaz:hasID>
    <adlgaz:hasModifiedDate rdf:datatype="http://www.w3.org/2001/XMLSchema#date"
    >2004-02-25</adlgaz:hasModifiedDate>
    <adlgaz:hasEntryDate rdf:datatype="http://www.w3.org/2001/XMLSchema#date"
    >1999-07-23</adlgaz:hasEntryDate>
    <adlgaz:hasExtent>MULTIPOINT(-110.01555633544922 39.215831756591797, -109.99555969238281 39.209720611572266)</adlgaz:hasExtent>
    <adlgaz:hasSchema>ADL Feature Type Thesaurus</adlgaz:hasSchema>
    <adlgaz:hasDescription></adlgaz:hasDescription>
    <adlgaz:onPlanet>Earth</adlgaz:onPlanet>
    <adlgaz:hasAlternateName xml:lang="NULL">Poverty Bench</adlgaz:hasAlternateName>
    <adlgaz:hasPrimaryName xml:lang="en">"Poverty Bench"</adlgaz:hasPrimaryName>
  </rdf:Description>
  <rdf:Description rdf:about="http://adl-gazetteer.geog.ucsb.edu/ADL/provo_bench">
    <adlgaz:hasID>6006406</adlgaz:hasID>
    <adlgaz:hasModifiedDate rdf:datatype="http://www.w3.org/2001/XMLSchema#date"
    >2004-02-25</adlgaz:hasModifiedDate>
    <adlgaz:hasEntryDate rdf:datatype="http://www.w3.org/2001/XMLSchema#date"
    >1999-07-23</adlgaz:hasEntryDate>
    <adlgaz:hasExtent>POINT (-111.6991729736328100 40.3013916015625000)</adlgaz:hasExtent>
    <adlgaz:hasSchema>ADL Feature Type Thesaurus</adlgaz:hasSchema>
    <adlgaz:hasDescription></adlgaz:hasDescription>
    <adlgaz:onPlanet>Earth</adlgaz:onPlanet>
    <adlgaz:hasAlternateName xml:lang="NULL">Provo Bench</adlgaz:hasAlternateName>
    <adlgaz:hasPrimaryName xml:lang="en">"Provo Bench"</adlgaz:hasPrimaryName>
  </rdf:Description>
  <rdf:Description rdf:about="http://adl-gazetteer.geog.ucsb.edu/ADL/pretty_tree_bench">
    <adlgaz:hasID>6006404</adlgaz:hasID>
    <adlgaz:hasModifiedDate rdf:datatype="http://www.w3.org/2001/XMLSchema#date"
    >2004-02-25</adlgaz:hasModifiedDate>
    <adlgaz:hasEntryDate rdf:datatype="http://www.w3.org/2001/XMLSchema#date"
    >1999-07-23</adlgaz:hasEntryDate>
    <adlgaz:hasExtent>POINT (-111.4538879394531200 37.9252815246582030)</adlgaz:hasExtent>
    <adlgaz:hasSchema>ADL Feature Type Thesaurus</adlgaz:hasSchema>
    <adlgaz:hasDescription></adlgaz:hasDescription>
    <adlgaz:onPlanet>Earth</adlgaz:onPlanet>
    <adlgaz:hasAlternateName xml:lang="NULL">Pretty Tree Bench</adlgaz:hasAlternateName>
    <adlgaz:hasPrimaryName xml:lang="en">"Pretty Tree Bench"</adlgaz:hasPrimaryName>
  </rdf:Description>
  <rdf:Description rdf:about="http://adl-gazetteer.geog.ucsb.edu/ADL/row_bench">
    <adlgaz:hasID>6006410</adlgaz:hasID>
    <adlgaz:hasModifiedDate rdf:datatype="http://www.w3.org/2001/XMLSchema#date"
    >2004-02-25</adlgaz:hasModifiedDate>
    <adlgaz:hasEntryDate rdf:datatype="http://www.w3.org/2001/XMLSchema#date"
    >1999-07-23</adlgaz:hasEntryDate>
    <adlgaz:hasExtent>POINT (-111.2797164916992200 40.3636093139648440)</adlgaz:hasExtent>
    <adlgaz:hasSchema>ADL Feature Type Thesaurus</adlgaz:hasSchema>
    <adlgaz:hasDescription></adlgaz:hasDescription>
    <adlgaz:onPlanet>Earth</adlgaz:onPlanet>
    <adlgaz:hasAlternateName xml:lang="NULL">Row Bench</adlgaz:hasAlternateName>
    <adlgaz:hasPrimaryName xml:lang="en">"Row Bench"</adlgaz:hasPrimaryName>
  </rdf:Description>
  <rdf:Description rdf:about="http://adl-gazetteer.geog.ucsb.edu/ADL/reynolds_point">
    <adlgaz:hasID>6006408</adlgaz:hasID>
    <adlgaz:hasModifiedDate rdf:datatype="http://www.w3.org/2001/XMLSchema#date"
    >2004-02-25</adlgaz:hasModifiedDate>
    <adlgaz:hasEntryDate rdf:datatype="http://www.w3.org/2001/XMLSchema#date"
    >1999-07-23</adlgaz:hasEntryDate>
    <adlgaz:hasExtent>POINT (-111.5680618286132800 37.3638916015625000)</adlgaz:hasExtent>
    <adlgaz:hasSchema>ADL Feature Type Thesaurus</adlgaz:hasSchema>
    <adlgaz:hasDescription></adlgaz:hasDescription>
    <adlgaz:onPlanet>Earth</adlgaz:onPlanet>
    <adlgaz:hasAlternateName xml:lang="NULL">Reynolds Point</adlgaz:hasAlternateName>
    <adlgaz:hasPrimaryName xml:lang="en">"Reynolds Point"</adlgaz:hasPrimaryName>
  </rdf:Description>
</rdf:RDF>
